<annotation>
  <folder>train</folder>
  <filename>62</filename>
  <path>C:\CTOS\Training\Training\data\images\train\62.jpg</path>
  <source>
    <database>Unknown</database>
  </source>
  <size>
    <width>800</width>
    <height>600</height>
    <depth>3</depth>
  </size>
  <segmented>0</segmented>
  <object>
    <name>gun</name>
    <pose>Unspecified</pose>
    <truncated>0</truncated>
    <difficult>0</difficult>
    <bndbox>
      <xmin>8</xmin>
      <ymin>35</ymin>
      <xmax>744</xmax>
      <ymax>518</ymax>
    </bndbox>
  </object>
</annotation>
