{
    "asset": {
        "format": "jpg",
        "id": "a69c1c8a83077b54a9019735445f78c1",
        "name": "113.jpg",
        "path": "file:C:/CTOS/object_detection/data/images/train/113.jpg",
        "size": {
            "width": 800,
            "height": 600
        },
        "state": 2,
        "type": 1
    },
    "regions": [
        {
            "id": "JEe-yXFFI",
            "type": "RECTANGLE",
            "tags": [
                "weapon"
            ],
            "boundingBox": {
                "height": 194.45407279029465,
                "width": 173.7321196358908,
                "left": 172.6918075422627,
                "top": 331.71577123050264
            },
            "points": [
                {
                    "x": 172.6918075422627,
                    "y": 331.71577123050264
                },
                {
                    "x": 346.42392717815346,
                    "y": 331.71577123050264
                },
                {
                    "x": 346.42392717815346,
                    "y": 526.1698440207973
                },
                {
                    "x": 172.6918075422627,
                    "y": 526.1698440207973
                }
            ]
        },
        {
            "id": "8yXOC-JAV",
            "type": "RECTANGLE",
            "tags": [
                "person"
            ],
            "boundingBox": {
                "height": 550.0866551126517,
                "width": 462.9388816644994,
                "left": 219.5058517555267,
                "top": 47.83362218370884
            },
            "points": [
                {
                    "x": 219.5058517555267,
                    "y": 47.83362218370884
                },
                {
                    "x": 682.4447334200261,
                    "y": 47.83362218370884
                },
                {
                    "x": 682.4447334200261,
                    "y": 597.9202772963605
                },
                {
                    "x": 219.5058517555267,
                    "y": 597.9202772963605
                }
            ]
        }
    ],
    "version": "2.0.0-preview.3"
}